{
  "locations": [
    {
      "lat": 13.748,
      "lon": 100.51,
      "time": 1546093260.0
    },
    {
      "lat": 13.7587,
      "lon": 100.4974,
      "time": 1546276980.0
    },
    {
      "lat": 14.3463,
      "lon": 100.5775,
      "time": 1546324620.0
    },
    {
      "lat": 14.3458,
      "lon": 100.5527,
      "time": 1546327440.0
    },
    {
      "lat": 14.3466,
      "lon": 100.5414,
      "time": 1546329120.0
    },
    {
      "lat": 14.3466,
      "lon": 100.5414,
      "time": 1546329180.0
    },
    {
      "lat": 14.348,
      "lon": 100.565,
      "time": 1546330740.0
    },
    {
      "lat": 18.865,
      "lon": 99.273,
      "time": 1546414320.0
    },
    {
      "lat": 18.786,
      "lon": 98.997,
      "time": 1546443660.0
    },
    {
      "lat": 18.675,
      "lon": 98.65,
      "time": 1546500960.0
    },
    {
      "lat": 18.675,
      "lon": 98.65,
      "time": 1546500961.0
    }
  ]
}